komeda/__init__.py
komeda-0.1.0.dist-info/METADATA
komeda-0.1.0.dist-info/WHEEL
komeda-0.1.0.dist-info/RECORD
