Metadata-Version: 2.3
Name: komeda
Version: 0.1.0
Summary: Komeda's coffee menu data
Author: Yoshiki Takagi
Author-email: yoshiki.tkg@gmail.com
Requires-Python: >=3.10
Classifier: Programming Language :: Python :: 3
Classifier: Programming Language :: Python :: 3.10
Classifier: Programming Language :: Python :: 3.11
Classifier: Programming Language :: Python :: 3.12
Classifier: Programming Language :: Python :: 3.13
Requires-Dist: pyyaml (>=6.0.2,<7.0.0)
